LICENSE
README.md
setup.cfg
setup.py
breeze_strategies/__init__.py
breeze_strategies/breeze_strategies.py
breeze_strategies.egg-info/PKG-INFO
breeze_strategies.egg-info/SOURCES.txt
breeze_strategies.egg-info/dependency_links.txt
breeze_strategies.egg-info/requires.txt
breeze_strategies.egg-info/top_level.txt