Metadata-Version: 2.1
Name: breeze_strategies
Version: 1.0.24
Summary: ICICIDIRECT's breezeconnect strategies in python
Home-page: https://github.com/Idirect-Tech/python_strategies/tree/master
Author: ICICI Direct Breeze
Author-email: breezeapi@icicisecurities.com
Classifier: Programming Language :: Python :: 3
Classifier: License :: OSI Approved :: MIT License
Classifier: Operating System :: OS Independent
Requires-Python: >=3.6
License-File: LICENSE
Requires-Dist: breeze_connect
Requires-Dist: nest_asyncio
Requires-Dist: IPython
